lutorpy
