Metadata-Version: 1.1
Name: lutorpy
Version: 1.3.7
Summary: Python wrapper for torch and Lua/LuaJIT
Home-page: https://github.com/oeway/lutorpy
Author: Wei OUYANG
Author-email: wei.ouyang@cri-paris.org
License: MIT style
Platform: UNKNOWN
Classifier: Development Status :: 5 - Production/Stable
Classifier: Intended Audience :: Developers
Classifier: Intended Audience :: Information Technology
Classifier: License :: OSI Approved :: MIT License
Classifier: Programming Language :: Cython
Classifier: Programming Language :: Python :: 2
Classifier: Programming Language :: Python :: 2.6
Classifier: Programming Language :: Python :: 2.7
Classifier: Programming Language :: Python :: 3
Classifier: Programming Language :: Python :: 3.2
Classifier: Programming Language :: Python :: 3.3
Classifier: Programming Language :: Python :: 3.4
Classifier: Programming Language :: Python :: 3.5
Classifier: Programming Language :: Other Scripting Engines
Classifier: Operating System :: OS Independent
Classifier: Topic :: Software Development
